Audio2Vec/__init__.py
Audio2Vec/audio2vec.py
speech2vec-0.6.12.dist-info/METADATA
speech2vec-0.6.12.dist-info/WHEEL
speech2vec-0.6.12.dist-info/top_level.txt
speech2vec-0.6.12.dist-info/RECORD
