Metadata-Version: 2.1
Name: speech2vec
Version: 0.6.12
Summary: An Audio2Vec annotation library
Home-page: https://github.com/dallo7/audio2Vec.git
Author: Dalmas Chituyi
Author-email: cwakhusama@gmail.com
License: GPL version 3, excluding DRM provisions
Requires-Dist: setuptools >=68.2.1
Requires-Dist: pandas >=2.0.1
Requires-Dist: scikit-learn >=1.4.0
